command_safe/__init__.py
command_safe/config.py
command_safe/main.py
command_safe/safe.py
command_safe-0.1.dist-info/DESCRIPTION.rst
command_safe-0.1.dist-info/METADATA
command_safe-0.1.dist-info/RECORD
command_safe-0.1.dist-info/WHEEL
command_safe-0.1.dist-info/entry_points.txt
command_safe-0.1.dist-info/metadata.json
command_safe-0.1.dist-info/top_level.txt
